README.md
setup.py
ACSGUI/Extraction.py
ACSGUI/__init__.py
ACSGUI/gui4.py
ACSGUI/key_test.py
ACSGUI/pdf_extract.py
ACSGUI.egg-info/PKG-INFO
ACSGUI.egg-info/SOURCES.txt
ACSGUI.egg-info/dependency_links.txt
ACSGUI.egg-info/requires.txt
ACSGUI.egg-info/top_level.txt